{"nodes": [{"id": "backend_services_lexicon_loader_py", "label": "lexicon_loader.py", "file_type": "code", "source_file": "backend\\services\\lexicon_loader.py", "source_location": "L1"}, {"id": "lexicon_loader_strip_diacritics", "label": "_strip_diacritics()", "file_type": "code", "source_file": "backend\\services\\lexicon_loader.py", "source_location": "L18"}, {"id": "lexicon_loader_normalize_phrases", "label": "_normalize_phrases()", "file_type": "code", "source_file": "backend\\services\\lexicon_loader.py", "source_location": "L24"}, {"id": "lexicon_loader_find_lexicon_path", "label": "_find_lexicon_path()", "file_type": "code", "source_file": "backend\\services\\lexicon_loader.py", "source_location": "L37"}, {"id": "lexicon_loader_get_lexicon", "label": "get_lexicon()", "file_type": "code", "source_file": "backend\\services\\lexicon_loader.py", "source_location": "L52"}, {"id": "lexicon_loader_rationale_19", "label": "Return the value without diacritics so ASCII variants can match.", "file_type": "rationale", "source_file": "backend\\services\\lexicon_loader.py", "source_location": "L19"}, {"id": "lexicon_loader_rationale_25", "label": "Lowercase phrases and add ASCII duplicates when they differ.", "file_type": "rationale", "source_file": "backend\\services\\lexicon_loader.py", "source_location": "L25"}, {"id": "lexicon_loader_rationale_53", "label": "Load and normalize the YAML lexicon for the given language.", "file_type": "rationale", "source_file": "backend\\services\\lexicon_loader.py", "source_location": "L53"}], "edges": [{"source": "backend_services_lexicon_loader_py", "target": "functools", "relation": "imports_from", "confidence": "EXTRACTED", "source_file": "backend\\services\\lexicon_loader.py", "source_location": "L4", "weight": 1.0}, {"source": "backend_services_lexicon_loader_py", "target": "pathlib", "relation": "imports_from", "confidence": "EXTRACTED", "source_file": "backend\\services\\lexicon_loader.py", "source_location": "L5", "weight": 1.0}, {"source": "backend_services_lexicon_loader_py", "target": "unicodedata", "relation": "imports", "confidence": "EXTRACTED", "source_file": "backend\\services\\lexicon_loader.py", "source_location": "L6", "weight": 1.0}, {"source": "backend_services_lexicon_loader_py", "target": "typing", "relation": "imports_from", "confidence": "EXTRACTED", "source_file": "backend\\services\\lexicon_loader.py", "source_location": "L7", "weight": 1.0}, {"source": "backend_services_lexicon_loader_py", "target": "yaml", "relation": "imports", "confidence": "EXTRACTED", "source_file": "backend\\services\\lexicon_loader.py", "source_location": "L9", "weight": 1.0}, {"source": "backend_services_lexicon_loader_py", "target": "lexicon_loader_strip_diacritics", "relation": "contains", "confidence": "EXTRACTED", "source_file": "backend\\services\\lexicon_loader.py", "source_location": "L18", "weight": 1.0}, {"source": "backend_services_lexicon_loader_py", "target": "lexicon_loader_normalize_phrases", "relation": "contains", "confidence": "EXTRACTED", "source_file": "backend\\services\\lexicon_loader.py", "source_location": "L24", "weight": 1.0}, {"source": "backend_services_lexicon_loader_py", "target": "lexicon_loader_find_lexicon_path", "relation": "contains", "confidence": "EXTRACTED", "source_file": "backend\\services\\lexicon_loader.py", "source_location": "L37", "weight": 1.0}, {"source": "backend_services_lexicon_loader_py", "target": "lexicon_loader_get_lexicon", "relation": "contains", "confidence": "EXTRACTED", "source_file": "backend\\services\\lexicon_loader.py", "source_location": "L52", "weight": 1.0}, {"source": "lexicon_loader_normalize_phrases", "target": "lexicon_loader_strip_diacritics", "relation": "calls", "confidence": "EXTRACTED", "source_file": "backend\\services\\lexicon_loader.py", "source_location": "L30", "weight": 1.0}, {"source": "lexicon_loader_get_lexicon", "target": "lexicon_loader_find_lexicon_path", "relation": "calls", "confidence": "EXTRACTED", "source_file": "backend\\services\\lexicon_loader.py", "source_location": "L54", "weight": 1.0}, {"source": "lexicon_loader_get_lexicon", "target": "lexicon_loader_normalize_phrases", "relation": "calls", "confidence": "EXTRACTED", "source_file": "backend\\services\\lexicon_loader.py", "source_location": "L60", "weight": 1.0}, {"source": "lexicon_loader_rationale_19", "target": "lexicon_loader_strip_diacritics", "relation": "rationale_for", "confidence": "EXTRACTED", "source_file": "backend\\services\\lexicon_loader.py", "source_location": "L19", "weight": 1.0}, {"source": "lexicon_loader_rationale_25", "target": "lexicon_loader_normalize_phrases", "relation": "rationale_for", "confidence": "EXTRACTED", "source_file": "backend\\services\\lexicon_loader.py", "source_location": "L25", "weight": 1.0}, {"source": "lexicon_loader_rationale_53", "target": "lexicon_loader_get_lexicon", "relation": "rationale_for", "confidence": "EXTRACTED", "source_file": "backend\\services\\lexicon_loader.py", "source_location": "L53", "weight": 1.0}]}